MMEdu/MMEdu.py
MMEdu/__init__.py
MMEdu/version.py
MMEdu/Classification/Classification_Edu.py
MMEdu/Classification/__init__.py
MMEdu/Classification/models/__init__.py
MMEdu/Classification/models/LeNet/LeNet.py
MMEdu/Classification/models/LeNet/__init__.py
MMEdu/Classification/models/MobileNet/MobileNet.py
MMEdu/Classification/models/MobileNet/__init__.py
MMEdu/Classification/models/RegNet/RegNet.py
MMEdu/Classification/models/RegNet/__init__.py
MMEdu/Classification/models/ResNeXt/__init__.py
MMEdu/Classification/models/ResNet18/ResNet18.py
MMEdu/Classification/models/ResNet18/__init__.py
MMEdu/Classification/models/ResNet50/ResNet50.py
MMEdu/Classification/models/ResNet50/__init__.py
MMEdu/Classification/models/VGG/__init__.py
MMEdu/Detection/Detection_Edu.py
MMEdu/Detection/__init__.py
MMEdu/Detection/demo/__init__.py
MMEdu/Detection/demo/demo.jpg
MMEdu/Detection/models/__init__.py
MMEdu/Detection/models/FasterRCNN/FasterRCNN.py
MMEdu/Detection/models/FasterRCNN/__init__.py
MMEdu/Detection/models/Mask_RCNN/Mask_RCNN.py
MMEdu/Detection/models/Mask_RCNN/__init__.py
MMEdu/Detection/models/SSD_Lite/SSD_Lite.py
MMEdu/Detection/models/SSD_Lite/__init__.py
MMEdu/Detection/models/Yolov3/Yolov3.py
MMEdu/Detection/models/Yolov3/__init__.py
MMEdu/Pose/Pose_Edu.py
MMEdu/Pose/__init__.py
MMEdu/Pose/models/__init__.py
MMEdu/Pose/models/FasterRCNNpose/FasterRCNNpose.py
MMEdu/Pose/models/FasterRCNNpose/__init__.py
MMEdu/Pose/models/HrNet/HrNet.py
MMEdu/Pose/models/HrNet/__init__.py
MMEdu/Pose/models/HrNet32/HrNet32.py
MMEdu/Pose/models/HrNet32/__init__.py
MMEdu/Pose/models/RTMPose/RTMPose.py
MMEdu/Pose/models/RTMPose/__init__.py
MMEdu/Pose/models/SCNet/SCNet.py
MMEdu/Pose/models/SCNet/__init__.py
MMEdu/examples/__init__.py
MMEdu/examples/ccc.py
MMEdu/examples/ccc1.py
MMEdu/examples/cls_demo.py
MMEdu/examples/convert_model.py
MMEdu/examples/det_demo.py
MMEdu/examples/gradio_demo.py
MMEdu/examples/pose_demo.py
mmedu-2.0.0.dist-info/METADATA
mmedu-2.0.0.dist-info/WHEEL
mmedu-2.0.0.dist-info/entry_points.txt
mmedu-2.0.0.dist-info/top_level.txt
mmedu-2.0.0.dist-info/zip-safe
mmedu-2.0.0.dist-info/RECORD
