Metadata-Version: 2.1
Name: MMEdu
Version: 2.0.0
Summary: MMEdu originates from the domestic artificial intelligence visual algorithm integration framework OpenMMLab, and is a "out of the box" deep learning development tool. Now supported by XEduPro
Home-page: https://github.com/XEduPro/OpenMMLab-Edu
Author: XEduPro
Author-email: easonqys@foxmail.com
License: MIT License
Requires-Python: >=3.6
Requires-Dist: mmcv-full ==1.4.5
Requires-Dist: mmcls ==0.20.0
Requires-Dist: mmdet ==2.23.0
Requires-Dist: torch ==1.8.1
Requires-Dist: torchvision ==0.9.1
Requires-Dist: matplotlib <=3.3.1
Requires-Dist: tqdm ==4.64.0
Requires-Dist: opencv-python >=4.1.2.30
Requires-Dist: onnx
Requires-Dist: onnxruntime
Requires-Dist: protobuf
